README.md
setup.cfg
setup.py
csgo_market_api/__init__.py
csgo_market_api/csgo_market.py
csgo_market_api.egg-info/PKG-INFO
csgo_market_api.egg-info/SOURCES.txt
csgo_market_api.egg-info/dependency_links.txt
csgo_market_api.egg-info/not-zip-safe
csgo_market_api.egg-info/requires.txt
csgo_market_api.egg-info/top_level.txt