Metadata-Version: 1.0
Name: csgo-market-api
Version: 0.1.1
Summary: A simple python module for interacting with various parts of market.csgo.com
Home-page: UNKNOWN
Author: UNKNOWN
Author-email: letsfunbox@gmail.com
License: UNKNOWN
Platform: UNKNOWN
